{"name":"Scratch extensions","tagline":"Savaka's extensions for ScratchX","body":"Table of links:\r\n\r\n| Name | Links |\r\n|---|:---:|\r\n| Debugging | [ScratchX](http://scratchx.org/?url=http://savaka2.github.io/scratch-extensions/debugging.js) [Doc](https://github.com/savaka2/scratch-extensions/wiki/Debugging-extension) [JavaScript](http://savaka2.github.io/scratch-extensions/debugging.js) |\r\n| Hash  | [ScratchX](http://scratchx.org/?url=http://savaka2.github.io/scratch-extensions/hash.js) [Doc](https://github.com/savaka2/scratch-extensions/wiki/Hash-extension) [JavaScript](http://savaka2.github.io/scratch-extensions/hash.js) |\r\n| JavaScript Dialogs | [ScratchX](http://scratchx.org/?url=http://savaka2.github.io/scratch-extensions/javascript-dialogs.js) [Doc](https://github.com/savaka2/scratch-extensions/wiki/JavaScript-Dialogs-extension) [JavaScript](http://savaka2.github.io/scratch-extensions/javascript-dialogs.js) |\r\n| Link Opener | [ScratchX](http://scratchx.org/?url=http://savaka2.github.io/scratch-extensions/link-opener.js) [Doc](https://github.com/savaka2/scratch-extensions/wiki/Link-Opener-extension) [JavaScript](http://savaka2.github.io/scratch-extensions/link-opener.js) |\r\n| Logic | [ScratchX](http://scratchx.org/?url=http://savaka2.github.io/scratch-extensions/logic.js) [Doc](https://github.com/savaka2/scratch-extensions/wiki/Logic-extension) [JavaScript](http://savaka2.github.io/scratch-extensions/logic.js) |\r\n| More Math | [ScratchX](http://scratchx.org/?url=http://savaka2.github.io/scratch-extensions/more-math.js) [Doc](https://github.com/savaka2/scratch-extensions/wiki/More-Math-extension) [JavaScript](http://savaka2.github.io/scratch-extensions/more-math.js) |\r\n| More Operators | [ScratchX](http://scratchx.org/?url=http://savaka2.github.io/scratch-extensions/more-operators.js) [Doc](https://github.com/savaka2/scratch-extensions/wiki/More-Operators-extension) [JavaScript](http://savaka2.github.io/scratch-extensions/more-operators.js) |\r\n| [Generic Links] | [Page](http://savaka2.github.io/scratch-extensions/) [Doc](https://github.com/savaka2/scratch-extensions/wiki) [GitHub](https://github.com/savaka2/scratch-extensions) |","google":"","note":"Don't delete this file! It's used internally to help with page regeneration."}